skateboard/__init__.py
skateboard/skateboard.py
skateboard/web/index.html
skateboard/web/skateboard.js
skateboard/web/styles.css
skateboard-0.0.1.dist-info/METADATA
skateboard-0.0.1.dist-info/WHEEL
skateboard-0.0.1.dist-info/licenses/LICENSE
skateboard-0.0.1.dist-info/RECORD
