Metadata-Version: 2.4
Name: skateboard
Version: 0.0.1
Summary: A minimal eel+ECharts dashboard interface
Author-email: Thomas Godden <thomas.godden@outlook.com>
License-Expression: MIT
License-File: LICENSE
Classifier: Operating System :: OS Independent
Classifier: Programming Language :: Python :: 3
Requires-Python: >=3.9
Requires-Dist: eel
Requires-Dist: numpy
